Metadata-Version: 1.0
Name: distributions-sri
Version: 0.2
Summary: Gaussian and Binomial distributions
Home-page: UNKNOWN
Author: Sridhar Sundaraju
Author-email: test@something.com
License: UNKNOWN
Platform: UNKNOWN
